migs/__init__.py
migs/cli.py
migs/gcloud.py
migs/ssh_config.py
migs/storage.py
migs-0.1.8.dist-info/licenses/LICENSE
migs-0.1.8.dist-info/METADATA
migs-0.1.8.dist-info/WHEEL
migs-0.1.8.dist-info/entry_points.txt
migs-0.1.8.dist-info/top_level.txt
migs-0.1.8.dist-info/RECORD
