Metadata-Version: 2.4
Name: migs
Version: 0.1.8
Summary: CLI tool for managing Google Cloud Managed Instance Groups
Author-email: Keaton Elvins <keatone@gmail.com>
License-Expression: MIT
Project-URL: Homepage, https://github.com/keatonelvins/migs
Project-URL: Documentation, https://github.com/keatonelvins/migs#readme
Project-URL: Repository, https://github.com/keatonelvins/migs.git
Project-URL: Issues, https://github.com/keatonelvins/migs/issues
Keywords: gcloud,google-cloud,mig,managed-instance-groups,cli
Classifier: Development Status :: 3 - Alpha
Classifier: Intended Audience :: Developers
Classifier: Programming Language :: Python :: 3
Classifier: Programming Language :: Python :: 3.8
Classifier: Programming Language :: Python :: 3.9
Classifier: Programming Language :: Python :: 3.10
Classifier: Programming Language :: Python :: 3.11
Classifier: Programming Language :: Python :: 3.12
Classifier: Operating System :: OS Independent
Classifier: Topic :: Software Development :: Libraries :: Python Modules
Classifier: Topic :: System :: Systems Administration
Classifier: Topic :: Utilities
Requires-Python: >=3.8
License-File: LICENSE
Requires-Dist: click>=8.0
Requires-Dist: rich>=13.0
Dynamic: license-file
